{"characters":[{"b":"Bhaiksuki","cp":72704,"n":"BHAIKSUKI LETTER A"},{"b":"Bhaiksuki","cp":72705,"n":"BHAIKSUKI LETTER AA"},{"b":"Bhaiksuki","cp":72706,"n":"BHAIKSUKI LETTER I"},{"b":"Bhaiksuki","cp":72707,"n":"BHAIKSUKI LETTER II"},{"b":"Bhaiksuki","cp":72708,"n":"BHAIKSUKI LETTER U"},{"b":"Bhaiksuki","cp":72709,"n":"BHAIKSUKI LETTER UU"},{"b":"Bhaiksuki","cp":72710,"n":"BHAIKSUKI LETTER VOCALIC R"},{"b":"Bhaiksuki","cp":72711,"n":"BHAIKSUKI LETTER VOCALIC RR"},{"b":"Bhaiksuki","cp":72712,"n":"BHAIKSUKI LETTER VOCALIC L"},{"b":"Bhaiksuki","cp":72714,"n":"BHAIKSUKI LETTER E"},{"b":"Bhaiksuki","cp":72715,"n":"BHAIKSUKI LETTER AI"},{"b":"Bhaiksuki","cp":72716,"n":"BHAIKSUKI LETTER O"},{"b":"Bhaiksuki","cp":72717,"n":"BHAIKSUKI LETTER AU"},{"b":"Bhaiksuki","cp":72718,"n":"BHAIKSUKI LETTER KA"},{"b":"Bhaiksuki","cp":72719,"n":"BHAIKSUKI LETTER KHA"},{"b":"Bhaiksuki","cp":72720,"n":"BHAIKSUKI LETTER GA"},{"b":"Bhaiksuki","cp":72721,"n":"BHAIKSUKI LETTER GHA"},{"b":"Bhaiksuki","cp":72722,"n":"BHAIKSUKI LETTER NGA"},{"b":"Bhaiksuki","cp":72723,"n":"BHAIKSUKI LETTER CA"},{"b":"Bhaiksuki","cp":72724,"n":"BHAIKSUKI LETTER CHA"},{"b":"Bhaiksuki","cp":72725,"n":"BHAIKSUKI LETTER JA"},{"b":"Bhaiksuki","cp":72726,"n":"BHAIKSUKI LETTER JHA"},{"b":"Bhaiksuki","cp":72727,"n":"BHAIKSUKI LETTER NYA"},{"b":"Bhaiksuki","cp":72728,"n":"BHAIKSUKI LETTER TTA"},{"b":"Bhaiksuki","cp":72729,"n":"BHAIKSUKI LETTER TTHA"},{"b":"Bhaiksuki","cp":72730,"n":"BHAIKSUKI LETTER DDA"},{"b":"Bhaiksuki","cp":72731,"n":"BHAIKSUKI LETTER DDHA"},{"b":"Bhaiksuki","cp":72732,"n":"BHAIKSUKI LETTER NNA"},{"b":"Bhaiksuki","cp":72733,"n":"BHAIKSUKI LETTER TA"},{"b":"Bhaiksuki","cp":72734,"n":"BHAIKSUKI LETTER THA"},{"b":"Bhaiksuki","cp":72735,"n":"BHAIKSUKI LETTER DA"},{"b":"Bhaiksuki","cp":72736,"n":"BHAIKSUKI LETTER DHA"},{"b":"Bhaiksuki","cp":72737,"n":"BHAIKSUKI LETTER NA"},{"b":"Bhaiksuki","cp":72738,"n":"BHAIKSUKI LETTER PA"},{"b":"Bhaiksuki","cp":72739,"n":"BHAIKSUKI LETTER PHA"},{"b":"Bhaiksuki","cp":72740,"n":"BHAIKSUKI LETTER BA"},{"b":"Bhaiksuki","cp":72741,"n":"BHAIKSUKI LETTER BHA"},{"b":"Bhaiksuki","cp":72742,"n":"BHAIKSUKI LETTER MA"},{"b":"Bhaiksuki","cp":72743,"n":"BHAIKSUKI LETTER YA"},{"b":"Bhaiksuki","cp":72744,"n":"BHAIKSUKI LETTER RA"},{"b":"Bhaiksuki","cp":72745,"n":"BHAIKSUKI LETTER LA"},{"b":"Bhaiksuki","cp":72746,"n":"BHAIKSUKI LETTER VA"},{"b":"Bhaiksuki","cp":72747,"n":"BHAIKSUKI LETTER SHA"},{"b":"Bhaiksuki","cp":72748,"n":"BHAIKSUKI LETTER SSA"},{"b":"Bhaiksuki","cp":72749,"n":"BHAIKSUKI LETTER SA"},{"b":"Bhaiksuki","cp":72750,"n":"BHAIKSUKI LETTER HA"},{"b":"Bhaiksuki","cp":72751,"n":"BHAIKSUKI VOWEL SIGN AA"},{"b":"Bhaiksuki","cp":72752,"n":"BHAIKSUKI VOWEL SIGN I"},{"b":"Bhaiksuki","cp":72753,"n":"BHAIKSUKI VOWEL SIGN II"},{"b":"Bhaiksuki","cp":72754,"n":"BHAIKSUKI VOWEL SIGN U"},{"b":"Bhaiksuki","cp":72755,"n":"BHAIKSUKI VOWEL SIGN UU"},{"b":"Bhaiksuki","cp":72756,"n":"BHAIKSUKI VOWEL SIGN VOCALIC R"},{"b":"Bhaiksuki","cp":72757,"n":"BHAIKSUKI VOWEL SIGN VOCALIC RR"},{"b":"Bhaiksuki","cp":72758,"n":"BHAIKSUKI VOWEL SIGN VOCALIC L"},{"b":"Bhaiksuki","cp":72760,"n":"BHAIKSUKI VOWEL SIGN E"},{"b":"Bhaiksuki","cp":72761,"n":"BHAIKSUKI VOWEL SIGN AI"},{"b":"Bhaiksuki","cp":72762,"n":"BHAIKSUKI VOWEL SIGN O"},{"b":"Bhaiksuki","cp":72763,"n":"BHAIKSUKI VOWEL SIGN AU"},{"b":"Bhaiksuki","cp":72764,"n":"BHAIKSUKI SIGN CANDRABINDU"},{"b":"Bhaiksuki","cp":72765,"n":"BHAIKSUKI SIGN ANUSVARA"},{"b":"Bhaiksuki","cp":72766,"n":"BHAIKSUKI SIGN VISARGA"},{"b":"Bhaiksuki","cp":72767,"n":"BHAIKSUKI SIGN VIRAMA"},{"b":"Bhaiksuki","cp":72768,"n":"BHAIKSUKI SIGN AVAGRAHA"},{"b":"Bhaiksuki","cp":72769,"n":"BHAIKSUKI DANDA"},{"b":"Bhaiksuki","cp":72770,"n":"BHAIKSUKI DOUBLE DANDA"},{"b":"Bhaiksuki","cp":72771,"n":"BHAIKSUKI WORD SEPARATOR"},{"b":"Bhaiksuki","cp":72772,"n":"BHAIKSUKI GAP FILLER-1"},{"b":"Bhaiksuki","cp":72773,"n":"BHAIKSUKI GAP FILLER-2"},{"b":"Bhaiksuki","cp":72784,"n":"BHAIKSUKI DIGIT ZERO"},{"b":"Bhaiksuki","cp":72785,"n":"BHAIKSUKI DIGIT ONE"},{"b":"Bhaiksuki","cp":72786,"n":"BHAIKSUKI DIGIT TWO"},{"b":"Bhaiksuki","cp":72787,"n":"BHAIKSUKI DIGIT THREE"},{"b":"Bhaiksuki","cp":72788,"n":"BHAIKSUKI DIGIT FOUR"},{"b":"Bhaiksuki","cp":72789,"n":"BHAIKSUKI DIGIT FIVE"},{"b":"Bhaiksuki","cp":72790,"n":"BHAIKSUKI DIGIT SIX"},{"b":"Bhaiksuki","cp":72791,"n":"BHAIKSUKI DIGIT SEVEN"},{"b":"Bhaiksuki","cp":72792,"n":"BHAIKSUKI DIGIT EIGHT"},{"b":"Bhaiksuki","cp":72793,"n":"BHAIKSUKI DIGIT NINE"},{"b":"Bhaiksuki","cp":72794,"n":"BHAIKSUKI NUMBER ONE"},{"b":"Bhaiksuki","cp":72795,"n":"BHAIKSUKI NUMBER TWO"},{"b":"Bhaiksuki","cp":72796,"n":"BHAIKSUKI NUMBER THREE"},{"b":"Bhaiksuki","cp":72797,"n":"BHAIKSUKI NUMBER FOUR"},{"b":"Bhaiksuki","cp":72798,"n":"BHAIKSUKI NUMBER FIVE"},{"b":"Bhaiksuki","cp":72799,"n":"BHAIKSUKI NUMBER SIX"},{"b":"Bhaiksuki","cp":72800,"n":"BHAIKSUKI NUMBER SEVEN"},{"b":"Bhaiksuki","cp":72801,"n":"BHAIKSUKI NUMBER EIGHT"},{"b":"Bhaiksuki","cp":72802,"n":"BHAIKSUKI NUMBER NINE"},{"b":"Bhaiksuki","cp":72803,"n":"BHAIKSUKI NUMBER TEN"},{"b":"Bhaiksuki","cp":72804,"n":"BHAIKSUKI NUMBER TWENTY"},{"b":"Bhaiksuki","cp":72805,"n":"BHAIKSUKI NUMBER THIRTY"},{"b":"Bhaiksuki","cp":72806,"n":"BHAIKSUKI NUMBER FORTY"},{"b":"Bhaiksuki","cp":72807,"n":"BHAIKSUKI NUMBER FIFTY"},{"b":"Bhaiksuki","cp":72808,"n":"BHAIKSUKI NUMBER SIXTY"},{"b":"Bhaiksuki","cp":72809,"n":"BHAIKSUKI NUMBER SEVENTY"},{"b":"Bhaiksuki","cp":72810,"n":"BHAIKSUKI NUMBER EIGHTY"},{"b":"Bhaiksuki","cp":72811,"n":"BHAIKSUKI NUMBER NINETY"},{"b":"Bhaiksuki","cp":72812,"n":"BHAIKSUKI HUNDREDS UNIT MARK"}],"count":97,"property":"Bhks"}